{
  "/_not-found": "app/_not-found.js",
  "/awards/page": "app/awards/page.js",
  "/matches/page": "app/matches/page.js",
  "/page": "app/page.js",
  "/login/page": "app/login/page.js",
  "/free-agency/page": "app/free-agency/page.js",
  "/players/page": "app/players/page.js",
  "/dashboard/page": "app/dashboard/page.js",
  "/teams/page": "app/teams/page.js",
  "/news/page": "app/news/page.js",
  "/standings/page": "app/standings/page.js",
  "/statistics/page": "app/statistics/page.js",
  "/register/page": "app/register/page.js"
}